Sel_Auto_Base/__init__.py
Sel_Auto_Base/sel_auto_base.py
sel_auto_base-0.1.2.dist-info/LICENSE
sel_auto_base-0.1.2.dist-info/METADATA
sel_auto_base-0.1.2.dist-info/WHEEL
sel_auto_base-0.1.2.dist-info/top_level.txt
sel_auto_base-0.1.2.dist-info/RECORD
